mlipaudit/__init__.py
mlipaudit/app.py
mlipaudit/benchmark.py
mlipaudit/benchmarks_cli.py
mlipaudit/exceptions.py
mlipaudit/io.py
mlipaudit/io_helpers.py
mlipaudit/main.py
mlipaudit/run_mode.py
mlipaudit/scoring.py
mlipaudit/app_data/conformer_selection/img/rsz_ado00.png
mlipaudit/app_data/conformer_selection/img/rsz_bpn00.png
mlipaudit/app_data/conformer_selection/img/rsz_efa00.png
mlipaudit/app_data/dihedral_scan/TorsionNet500_nocoord.json
mlipaudit/app_data/dihedral_scan/img/fragment_001.png
mlipaudit/app_data/dihedral_scan/img/fragment_002.png
mlipaudit/app_data/dihedral_scan/img/fragment_003.png
mlipaudit/app_data/dihedral_scan/img/fragment_004.png
mlipaudit/app_data/dihedral_scan/img/fragment_005.png
mlipaudit/app_data/dihedral_scan/img/fragment_006.png
mlipaudit/app_data/dihedral_scan/img/fragment_007.png
mlipaudit/app_data/dihedral_scan/img/fragment_008.png
mlipaudit/app_data/dihedral_scan/img/fragment_009.png
mlipaudit/app_data/dihedral_scan/img/fragment_010.png
mlipaudit/app_data/dihedral_scan/img/fragment_011.png
mlipaudit/app_data/dihedral_scan/img/fragment_012.png
mlipaudit/app_data/dihedral_scan/img/fragment_013.png
mlipaudit/app_data/dihedral_scan/img/fragment_014.png
mlipaudit/app_data/dihedral_scan/img/fragment_015.png
mlipaudit/app_data/dihedral_scan/img/fragment_016.png
mlipaudit/app_data/dihedral_scan/img/fragment_017.png
mlipaudit/app_data/dihedral_scan/img/fragment_018.png
mlipaudit/app_data/dihedral_scan/img/fragment_019.png
mlipaudit/app_data/dihedral_scan/img/fragment_020.png
mlipaudit/app_data/dihedral_scan/img/fragment_021.png
mlipaudit/app_data/dihedral_scan/img/fragment_022.png
mlipaudit/app_data/dihedral_scan/img/fragment_023.png
mlipaudit/app_data/dihedral_scan/img/fragment_024.png
mlipaudit/app_data/dihedral_scan/img/fragment_025.png
mlipaudit/app_data/dihedral_scan/img/fragment_026.png
mlipaudit/app_data/dihedral_scan/img/fragment_027.png
mlipaudit/app_data/dihedral_scan/img/fragment_028.png
mlipaudit-0.1.1.dist-info/METADATA
mlipaudit-0.1.1.dist-info/WHEEL
mlipaudit-0.1.1.dist-info/entry_points.txt
mlipaudit-0.1.1.dist-info/RECORD
