Metadata-Version: 2.4
Name: mlipaudit
Version: 0.1.1
Summary: Library and CLI tool for benchmarking ML Interatomic Potentials
Project-URL: Homepage, https://github.com/instadeepai/mlipaudit/
Author-email: InstaDeep <placeholder@instadeep.com>
Requires-Python: >=3.11
Requires-Dist: huggingface-hub>=0.33.4
Requires-Dist: jax-md>=0.2.26
Requires-Dist: mdtraj>=1.10.3
Requires-Dist: mlip>=0.1.6
Requires-Dist: scikit-learn>=1.7.0
Requires-Dist: streamlit>=1.46.1
Requires-Dist: tmtools>=0.2.0
Requires-Dist: vl-convert-python>=1.8.0
Provides-Extra: cuda
Requires-Dist: mlip[cuda]>=0.1.6; extra == 'cuda'
